CHANGES.txt
LICENSE.txt
MANIFEST.in
README.md
requirements.txt
setup.py
mr3px/__init__.py
mr3px/common.py
mr3px/csvprotocol.py
mr3px/keyedjson.py
mr3px/mysqldump.py
mr3px/yaml.py
mr3px.egg-info/PKG-INFO
mr3px.egg-info/SOURCES.txt
mr3px.egg-info/dependency_links.txt
mr3px.egg-info/requires.txt
mr3px.egg-info/top_level.txt