Metadata-Version: 1.1
Name: mr3px
Version: 0.5.0
Summary: Line-based protocols for use with mrjob.
Home-page: http://github.com/msharp/mr3px
Author: David Marin, Max Sharples
Author-email: maxsharples@gmail.com
License: Apache
Platform: UNKNOWN
Classifier: Development Status :: 4 - Beta
Classifier: Intended Audience :: Developers
Classifier: License :: OSI Approved :: Apache Software License
Classifier: Natural Language :: English
Classifier: Operating System :: OS Independent
Classifier: Programming Language :: Python
Classifier: Programming Language :: Python :: 2.6
Classifier: Programming Language :: Python :: 2.7
Classifier: Programming Language :: Python :: 3.5
Classifier: Topic :: Database
Provides: mr3px
